statistika/__init__.py
statistika/papuyu.py
statistika/data/statistik_iwak_papuyu.csv
pilkommedia-0.1.3.dist-info/METADATA
pilkommedia-0.1.3.dist-info/WHEEL
pilkommedia-0.1.3.dist-info/top_level.txt
pilkommedia-0.1.3.dist-info/RECORD
