Metadata-Version: 2.1
Name: pilkommedia
Version: 0.1.3
Summary: Modul untuk keperluan perkuliahan Program Studi Pendidikan Komputer Universitas Lambung Mangkurat
Home-page: https://github.com/ahmadyogi543/pypi_pilkommedia
Author: Ahmad Yogi
Author-email: ahmadyogi543@gmail.com
Classifier: Programming Language :: Python :: 3
Classifier: License :: OSI Approved :: MIT License
Classifier: Operating System :: OS Independent
Requires-Python: >=3.6
Requires-Dist: setuptools
